{ "height":11,
 "infinite":false,
 "layers":[
        {
         "data":[194, 194, 194, 194, 194, 194, 194, 194, 194, 194, 194, 194, 194, 194, 194, 194, 194, 194, 194, 194, 1593, 194, 194, 194, 194, 194, 194, 194, 194, 194, 194, 194, 194, 194, 194, 194, 194, 194, 194, 194, 194, 1593, 163, 163, 163, 163, 163, 163, 163, 163, 163, 163, 163, 163, 163, 163, 163, 163, 163, 163, 163, 163, 1593, 163, 163, 163, 163, 163, 163, 163, 163, 163, 163, 163, 163, 163, 163, 163, 163, 163, 163, 163, 163, 1593, 163, 163, 163, 163, 163, 163, 163, 163, 163, 163, 163, 163, 163, 163, 163, 163, 163, 163, 163, 163, 1593, 163, 163, 163, 163, 163, 163, 163, 163, 163, 163, 163, 163, 163, 163, 163, 163, 163, 163, 163, 163, 1593, 163, 163, 163, 163, 163, 163, 163, 163, 163, 163, 163, 163, 163, 163, 163, 163, 163, 163, 163, 163, 1593, 163, 163, 163, 163, 163, 163, 163, 163, 163, 163, 163, 163, 163, 163, 163, 163, 163, 163, 163, 163, 1593, 163, 163, 163, 163, 163, 163, 163, 163, 163, 163, 163, 163, 163, 163, 163, 163, 163, 163, 163, 163, 1633, 163, 163, 163, 163, 163, 163, 163, 163, 163, 163, 163, 163, 163, 163, 163, 163, 163, 163, 163, 163, 1633, 121, 121, 121, 121, 121, 121, 121, 121, 121, 121, 121, 121, 121, 121, 121, 121, 121, 121, 121, 121, 121],
         "height":11,
         "id":1,
         "name":"Layer1",
         "opacity":1,
         "properties":[
                {
                 "name":"collisions",
                 "type":"bool",
                 "value":false
                }, 
                {
                 "name":"destroyedCollector",
                 "type":"bool",
                 "value":false
                }, 
                {
                 "name":"zIndex",
                 "type":"int",
                 "value":0
                }],
         "type":"tilelayer",
         "visible":true,
         "width":21,
         "x":0,
         "y":0
        }, 
        {
         "data":[0, 0, 2257, 0, 0, 0, 0, 2257, 0, 0, 0, 0, 0, 2257, 0, 0, 0, 0, 2257, 0, 0, 0, 0, 2297, 0, 0, 0, 0, 2297, 0, 0, 0, 0, 0, 2297, 0, 0, 0, 0, 2297, 0, 0, 0, 0, 0, 0, 0, 0, 0, 0, 1413, 567, 567, 567, 1414, 0, 0, 0, 0, 0, 0, 0, 0, 0, 0, 0, 0, 0, 0, 0, 0, 527, 1374, 1374, 1374, 568, 0, 0, 0, 0, 0, 0, 0, 0, 567, 567, 567, 567, 567, 567, 567, 567, 1374, 1374, 1374, 1374, 568, 0, 0, 0, 0, 0, 0, 0, 0, 1374, 1374, 1374, 1374, 1374, 1374, 1374, 1374, 1374, 1374, 1374, 1374, 568, 0, 0, 0, 0, 0, 0, 0, 0, 528, 528, 528, 528, 528, 528, 528, 528, 528, 528, 528, 528, 1454, 0, 0, 0, 0, 0, 0, 0, 0, 0, 0, 0, 0, 0, 0, 0, 0, 0, 0, 0, 0, 0, 0, 0, 0, 0, 0, 0, 0, 0, 0, 0, 0, 0, 0, 0, 0, 0, 0, 0, 0, 0, 0, 0, 0, 0, 0, 0, 0, 0, 0, 0, 0, 0, 0, 0, 0, 0, 0, 0, 0, 0, 0, 0, 0, 0, 0, 0, 0, 0, 0, 0, 0, 0, 0, 0, 0, 0, 0, 0, 0, 0, 0, 0, 0, 0, 0, 0, 0, 0, 0, 0, 0],
         "height":11,
         "id":2,
         "name":"Layer2",
         "opacity":1,
         "properties":[
                {
                 "name":"collisions",
                 "type":"bool",
                 "value":false
                }, 
                {
                 "name":"destroyedCollector",
                 "type":"bool",
                 "value":false
                }, 
                {
                 "name":"zIndex",
                 "type":"int",
                 "value":0
                }],
         "type":"tilelayer",
         "visible":true,
         "width":21,
         "x":0,
         "y":0
        }, 
        {
         "data":[0, 0, 0, 2419, 2029, 0, 0, 0, 2419, 0, 2030, 0, 2419, 0, 0, 0, 2029, 2419, 0, 0, 0, 0, 0, 0, 0, 0, 0, 0, 0, 0, 2263, 2264, 2265, 0, 0, 0, 0, 0, 0, 0, 0, 0, 0, 0, 0, 0, 0, 0, 0, 1871, 0, 2303, 2304, 2305, 0, 1872, 0, 0, 0, 0, 0, 0, 0, 2062, 0, 0, 0, 0, 0, 0, 0, 0, 0, 0, 0, 0, 0, 0, 0, 0, 0, 0, 0, 0, 0, 0, 0, 0, 0, 0, 0, 0, 0, 0, 0, 0, 0, 0, 0, 0, 0, 0, 0, 0, 0, 0, 0, 0, 0, 0, 0, 0, 0, 0, 0, 0, 0, 0, 0, 0, 0, 0, 0, 0, 1791, 0, 0, 0, 0, 0, 0, 0, 0, 0, 0, 0, 0, 0, 0, 0, 0, 0, 0, 0, 0, 1831, 0, 0, 0, 0, 0, 0, 0, 0, 0, 0, 0, 0, 0, 0, 0, 0, 0, 0, 0, 0, 2063, 0, 0, 0, 0, 0, 0, 0, 0, 0, 0, 0, 0, 0, 0, 0, 0, 0, 0, 0, 0, 0, 0, 0, 0, 0, 0, 0, 0, 0, 0, 0, 0, 0, 0, 0, 0, 0, 0, 0, 0, 0, 0, 0, 0, 0, 0, 0, 0, 0, 0, 0, 0, 0, 0, 0, 0, 0, 0, 0, 0, 0, 0, 0, 0],
         "height":11,
         "id":7,
         "name":"Layer3",
         "opacity":1,
         "properties":[
                {
                 "name":"collisions",
                 "type":"bool",
                 "value":false
                }, 
                {
                 "name":"destroyedCollector",
                 "type":"bool",
                 "value":true
                }, 
                {
                 "name":"zIndex",
                 "type":"int",
                 "value":0
                }],
         "type":"tilelayer",
         "visible":true,
         "width":21,
         "x":0,
         "y":0
        }, 
        {
         "data":[0, 0, 0, 0, 0, 0, 0, 0, 0, 0, 0, 0, 0, 0, 0, 0, 0, 0, 0, 0, 0, 2345, 0, 0, 1539, 1540, 0, 0, 0, 0, 0, 0, 0, 0, 0, 0, 1538, 1539, 1540, 0, 2345, 0, 2385, 0, 0, 1579, 1580, 0, 0, 0, 0, 0, 0, 0, 0, 0, 0, 1578, 1579, 1580, 0, 2385, 0, 0, 0, 0, 0, 0, 0, 0, 0, 0, 0, 0, 0, 0, 0, 0, 0, 0, 0, 0, 0, 0, 0, 0, 0, 0, 0, 0, 0, 0, 0, 0, 0, 0, 0, 0, 0, 0, 0, 0, 0, 0, 0, 0, 0, 0, 0, 0, 0, 0, 0, 0, 0, 0, 0, 0, 0, 0, 0, 0, 0, 0, 0, 0, 0, 0, 0, 0, 0, 0, 0, 0, 0, 0, 0, 0, 0, 0, 0, 0, 0, 0, 0, 0, 0, 1791, 0, 0, 0, 0, 0, 0, 0, 0, 0, 0, 0, 0, 0, 0, 0, 0, 0, 0, 0, 0, 1831, 0, 0, 0, 0, 0, 0, 0, 0, 0, 0, 0, 0, 0, 0, 0, 0, 0, 0, 0, 0, 0, 0, 0, 0, 0, 0, 0, 0, 0, 0, 0, 0, 0, 0, 0, 0, 0, 0, 0, 0, 0, 0, 0, 0, 0, 0, 0, 0, 0, 0, 0, 0, 0, 0, 0, 0, 0, 0, 0, 0, 0, 0],
         "height":11,
         "id":3,
         "name":"z-index-3",
         "opacity":1,
         "properties":[
                {
                 "name":"collisions",
                 "type":"bool",
                 "value":false
                }, 
                {
                 "name":"zIndex",
                 "type":"int",
                 "value":3
                }],
         "type":"tilelayer",
         "visible":true,
         "width":21,
         "x":0,
         "y":0
        }, 
        {
         "data":[0, 0, 0, 0, 0, 0, 0, 0, 0, 0, 0, 0, 0, 0, 0, 0, 0, 0, 0, 0, 0, 0, 0, 0, 0, 0, 0, 0, 0, 0, 0, 0, 0, 0, 0, 0, 0, 0, 0, 0, 0, 0, 0, 0, 0, 0, 0, 0, 0, 0, 0, 0, 0, 0, 0, 0, 0, 0, 0, 0, 0, 0, 0, 0, 0, 0, 0, 0, 0, 0, 0, 0, 0, 0, 0, 0, 0, 0, 0, 0, 0, 0, 0, 0, 0, 0, 0, 0, 0, 0, 0, 0, 0, 0, 0, 0, 0, 0, 0, 0, 0, 0, 0, 0, 0, 0, 0, 0, 0, 0, 0, 0, 2346, 0, 0, 0, 0, 0, 2347, 0, 0, 0, 0, 0, 0, 0, 0, 0, 0, 0, 0, 0, 0, 2386, 0, 0, 0, 0, 0, 2387, 0, 0, 0, 0, 0, 0, 0, 0, 0, 0, 0, 0, 0, 0, 0, 0, 0, 0, 0, 0, 0, 0, 0, 0, 0, 0, 0, 0, 0, 0, 0, 0, 0, 0, 0, 0, 0, 0, 0, 0, 0, 0, 0, 0, 0, 0, 0, 0, 0, 0, 0, 0, 0, 0, 0, 0, 0, 0, 0, 0, 0, 0, 0, 0, 0, 0, 0, 0, 0, 0, 0, 0, 0, 0, 0, 0, 0, 0, 0, 0, 0, 0, 0, 0, 0, 0, 0, 0, 0, 0, 0],
         "height":11,
         "id":8,
         "name":"z-index-7",
         "opacity":1,
         "properties":[
                {
                 "name":"collisions",
                 "type":"bool",
                 "value":false
                }, 
                {
                 "name":"zIndex",
                 "type":"int",
                 "value":7
                }],
         "type":"tilelayer",
         "visible":true,
         "width":21,
         "x":0,
         "y":0
        }, 
        {
         "data":[0, 0, 0, 0, 0, 0, 0, 0, 0, 0, 0, 0, 0, 0, 0, 0, 0, 0, 0, 0, 0, 0, 0, 0, 0, 0, 0, 0, 0, 0, 0, 0, 0, 0, 0, 0, 0, 0, 0, 0, 0, 0, 0, 0, 0, 0, 0, 0, 0, 0, 0, 0, 0, 0, 0, 0, 0, 0, 0, 0, 0, 0, 0, 0, 0, 0, 0, 0, 0, 0, 0, 0, 0, 0, 0, 0, 0, 0, 0, 0, 0, 0, 0, 0, 0, 0, 0, 0, 0, 0, 0, 0, 0, 0, 0, 0, 0, 0, 0, 0, 0, 0, 0, 0, 0, 0, 0, 0, 0, 0, 0, 0, 0, 0, 0, 0, 0, 0, 0, 0, 0, 0, 0, 0, 0, 0, 0, 0, 0, 0, 0, 0, 0, 1612, 1613, 1613, 1613, 1613, 1613, 1614, 0, 0, 0, 0, 0, 0, 0, 0, 0, 0, 0, 0, 0, 0, 1652, 1653, 1653, 1653, 1653, 1653, 1654, 0, 0, 0, 0, 0, 0, 0, 0, 0, 0, 0, 0, 0, 0, 0, 0, 0, 0, 0, 0, 0, 0, 0, 0, 0, 0, 0, 0, 0, 0, 0, 0, 0, 0, 0, 0, 0, 0, 0, 0, 0, 0, 0, 0, 0, 0, 0, 0, 0, 0, 0, 0, 0, 0, 0, 0, 0, 0, 0, 0, 0, 0, 0, 0, 0, 0, 0, 0, 0, 0],
         "height":11,
         "id":9,
         "name":"z-index-8",
         "opacity":1,
         "properties":[
                {
                 "name":"collisions",
                 "type":"bool",
                 "value":false
                }, 
                {
                 "name":"zIndex",
                 "type":"int",
                 "value":8
                }],
         "type":"tilelayer",
         "visible":true,
         "width":21,
         "x":0,
         "y":0
        }, 
        {
         "data":[0, 0, 0, 0, 0, 0, 0, 0, 0, 0, 0, 0, 0, 0, 0, 0, 0, 0, 0, 0, 0, 0, 0, 0, 0, 0, 0, 0, 0, 0, 0, 0, 0, 0, 0, 0, 0, 0, 0, 0, 0, 0, 0, 0, 0, 0, 0, 0, 0, 0, 0, 0, 0, 0, 0, 0, 0, 0, 0, 0, 0, 0, 0, 0, 0, 0, 0, 0, 0, 0, 0, 0, 0, 0, 0, 0, 0, 0, 0, 0, 0, 0, 0, 0, 0, 0, 0, 0, 0, 0, 0, 0, 0, 0, 0, 0, 0, 0, 0, 0, 0, 0, 0, 0, 0, 0, 0, 0, 0, 0, 0, 0, 0, 0, 0, 0, 0, 0, 0, 0, 0, 0, 0, 0, 0, 0, 0, 0, 0, 0, 0, 0, 0, 0, 0, 0, 0, 0, 0, 0, 0, 0, 0, 0, 0, 0, 0, 0, 0, 0, 0, 0, 0, 0, 0, 0, 0, 0, 0, 0, 0, 0, 0, 0, 0, 0, 0, 0, 2345, 0, 0, 0, 0, 0, 0, 0, 0, 0, 0, 0, 0, 0, 0, 0, 0, 0, 0, 2345, 0, 2385, 0, 0, 0, 0, 0, 0, 0, 0, 0, 0, 0, 0, 0, 0, 0, 0, 0, 0, 2385, 0, 0, 0, 0, 0, 0, 0, 0, 0, 0, 0, 0, 0, 0, 0, 0, 0, 0, 0, 0, 0, 0],
         "height":11,
         "id":10,
         "name":"z-index-10",
         "opacity":1,
         "properties":[
                {
                 "name":"collisions",
                 "type":"bool",
                 "value":false
                }, 
                {
                 "name":"zIndex",
                 "type":"int",
                 "value":10
                }],
         "type":"tilelayer",
         "visible":true,
         "width":21,
         "x":0,
         "y":0
        }, 
        {
         "draworder":"topdown",
         "id":14,
         "name":"collisions",
         "objects":[
                {
                 "height":96,
                 "id":2,
                 "name":"",
                 "rotation":0,
                 "type":"square",
                 "visible":true,
                 "width":32,
                 "x":0,
                 "y":224
                }, 
                {
                 "height":64,
                 "id":3,
                 "name":"",
                 "rotation":0,
                 "type":"square",
                 "visible":true,
                 "width":672,
                 "x":0,
                 "y":0
                }, 
                {
                 "height":256,
                 "id":4,
                 "name":"",
                 "rotation":0,
                 "type":"square",
                 "visible":true,
                 "width":32,
                 "x":640,
                 "y":64
                }, 
                {
                 "height":32,
                 "id":5,
                 "name":"",
                 "rotation":0,
                 "type":"square",
                 "visible":true,
                 "width":672,
                 "x":0,
                 "y":320
                }, 
                {
                 "height":32,
                 "id":7,
                 "name":"",
                 "rotation":0,
                 "type":"square",
                 "visible":true,
                 "width":200,
                 "x":239,
                 "y":224
                }, 
                {
                 "height":32,
                 "id":22,
                 "name":"",
                 "rotation":0,
                 "type":"square",
                 "visible":true,
                 "width":96,
                 "x":480,
                 "y":64
                }, 
                {
                 "height":64,
                 "id":54,
                 "name":"",
                 "rotation":0,
                 "type":"square",
                 "visible":true,
                 "width":32,
                 "x":0,
                 "y":64
                }, 
                {
                 "height":32,
                 "id":55,
                 "name":"",
                 "rotation":0,
                 "type":"square",
                 "visible":true,
                 "width":64,
                 "x":96,
                 "y":64
                }, 
                {
                 "height":32,
                 "id":56,
                 "name":"",
                 "rotation":0,
                 "type":"square",
                 "visible":true,
                 "width":32,
                 "x":224,
                 "y":192
                }, 
                {
                 "height":32,
                 "id":57,
                 "name":"",
                 "rotation":0,
                 "type":"square",
                 "visible":true,
                 "width":32,
                 "x":416,
                 "y":192
                }, 
                {
                 "height":32,
                 "id":58,
                 "name":"",
                 "rotation":0,
                 "type":"square",
                 "visible":true,
                 "width":65.3333333333333,
                 "x":301.333333333333,
                 "y":64
                }, 
                {
                 "height":32,
                 "id":59,
                 "name":"",
                 "rotation":0,
                 "type":"square",
                 "visible":true,
                 "width":32,
                 "x":416,
                 "y":64
                }, 
                {
                 "height":32,
                 "id":60,
                 "name":"",
                 "rotation":0,
                 "type":"square",
                 "visible":true,
                 "width":32,
                 "x":224,
                 "y":64
                }, 
                {
                 "height":96,
                 "id":61,
                 "name":"",
                 "rotation":0,
                 "type":"square",
                 "visible":true,
                 "width":32,
                 "x":608,
                 "y":160
                }, 
                {
                 "height":32,
                 "id":62,
                 "name":"",
                 "rotation":0,
                 "type":"square",
                 "visible":true,
                 "width":32,
                 "x":608,
                 "y":288
                }, 
                {
                 "height":32,
                 "id":63,
                 "name":"",
                 "rotation":0,
                 "type":"square",
                 "visible":true,
                 "width":32,
                 "x":608,
                 "y":64
                }],
         "opacity":1,
         "properties":[
                {
                 "name":"collisions",
                 "type":"bool",
                 "value":true
                }, 
                {
                 "name":"destructible",
                 "type":"bool",
                 "value":false
                }, 
                {
                 "name":"zIndex",
                 "type":"int",
                 "value":11
                }],
         "type":"objectgroup",
         "visible":true,
         "x":0,
         "y":0
        }, 
        {
         "draworder":"topdown",
         "id":15,
         "name":"destructibles",
         "objects":[],
         "opacity":1,
         "properties":[
                {
                 "name":"collisions",
                 "type":"bool",
                 "value":true
                }, 
                {
                 "name":"destructible",
                 "type":"bool",
                 "value":true
                }, 
                {
                 "name":"zIndex",
                 "type":"int",
                 "value":9
                }],
         "type":"objectgroup",
         "visible":true,
         "x":0,
         "y":0
        }, 
        {
         "draworder":"topdown",
         "id":17,
         "name":"ennemis",
         "objects":[
                {
                 "height":32,
                 "id":49,
                 "name":"",
                 "rotation":0,
                 "type":"ennemiMasse",
                 "visible":true,
                 "width":32,
                 "x":288,
                 "y":128
                }, 
                {
                 "height":32,
                 "id":50,
                 "name":"",
                 "rotation":0,
                 "type":"ennemiMasse",
                 "visible":true,
                 "width":32,
                 "x":320,
                 "y":256
                }, 
                {
                 "height":32,
                 "id":64,
                 "name":"",
                 "rotation":0,
                 "type":"ennemiMasse",
                 "visible":true,
                 "width":32,
                 "x":352,
                 "y":128
                }],
         "opacity":1,
         "properties":[
                {
                 "name":"ennemis",
                 "type":"bool",
                 "value":true
                }],
         "type":"objectgroup",
         "visible":true,
         "x":0,
         "y":0
        }, 
        {
         "draworder":"topdown",
         "id":19,
         "name":"items",
         "objects":[
                {
                 "height":32,
                 "id":65,
                 "name":"treasure",
                 "properties":[
                        {
                         "name":"treasureID",
                         "type":"int",
                         "value":17
                        }],
                 "rotation":0,
                 "type":"9",
                 "visible":true,
                 "width":32,
                 "x":576,
                 "y":96
                }, 
                {
                 "height":32,
                 "id":66,
                 "name":"treasure",
                 "properties":[
                        {
                         "name":"treasureID",
                         "type":"int",
                         "value":23
                        }],
                 "rotation":0,
                 "type":"0",
                 "visible":true,
                 "width":32,
                 "x":512,
                 "y":288
                }, 
                {
                 "height":32,
                 "id":67,
                 "name":"treasure",
                 "properties":[
                        {
                         "name":"treasureID",
                         "type":"int",
                         "value":22
                        }],
                 "rotation":0,
                 "type":"0",
                 "visible":true,
                 "width":32,
                 "x":416,
                 "y":288
                }, 
                {
                 "height":32,
                 "id":68,
                 "name":"treasure",
                 "properties":[
                        {
                         "name":"treasureID",
                         "type":"int",
                         "value":21
                        }],
                 "rotation":0,
                 "type":"0",
                 "visible":true,
                 "width":32,
                 "x":256,
                 "y":288
                }, 
                {
                 "height":32,
                 "id":69,
                 "name":"treasure",
                 "properties":[
                        {
                         "name":"treasureID",
                         "type":"int",
                         "value":20
                        }],
                 "rotation":0,
                 "type":"0",
                 "visible":true,
                 "width":32,
                 "x":64,
                 "y":288
                }, 
                {
                 "height":32,
                 "id":70,
                 "name":"treasure",
                 "properties":[
                        {
                         "name":"treasureID",
                         "type":"int",
                         "value":15
                        }],
                 "rotation":0,
                 "type":"0",
                 "visible":true,
                 "width":32,
                 "x":64,
                 "y":96
                }, 
                {
                 "height":32,
                 "id":71,
                 "name":"treasure",
                 "properties":[
                        {
                         "name":"treasureID",
                         "type":"int",
                         "value":16
                        }],
                 "rotation":0,
                 "type":"0",
                 "visible":true,
                 "width":32,
                 "x":192,
                 "y":96
                }, 
                {
                 "height":32,
                 "id":72,
                 "name":"treasure",
                 "properties":[
                        {
                         "name":"treasureID",
                         "type":"int",
                         "value":18
                        }],
                 "rotation":0,
                 "type":"1",
                 "visible":true,
                 "width":32,
                 "x":160,
                 "y":192
                }, 
                {
                 "height":32,
                 "id":73,
                 "name":"treasure",
                 "properties":[
                        {
                         "name":"treasureID",
                         "type":"int",
                         "value":19
                        }],
                 "rotation":0,
                 "type":"3",
                 "visible":true,
                 "width":32,
                 "x":512,
                 "y":192
                }, 
                {
                 "height":32,
                 "id":74,
                 "name":"nodeJS",
                 "rotation":0,
                 "type":"",
                 "visible":true,
                 "width":32,
                 "x":320,
                 "y":128
                }],
         "opacity":1,
         "properties":[
                {
                 "name":"items",
                 "type":"bool",
                 "value":true
                }],
         "type":"objectgroup",
         "visible":true,
         "x":0,
         "y":0
        }, 
        {
         "draworder":"topdown",
         "id":18,
         "name":"exits",
         "objects":[
                {
                 "height":96,
                 "id":53,
                 "name":"",
                 "rotation":0,
                 "type":"west",
                 "visible":true,
                 "width":32,
                 "x":0,
                 "y":128
                }],
         "opacity":1,
         "properties":[
                {
                 "name":"exit",
                 "type":"bool",
                 "value":true
                }],
         "type":"objectgroup",
         "visible":true,
         "x":0,
         "y":0
        }, 
        {
         "data":[0, 0, 0, 0, 0, 0, 0, 0, 0, 0, 0, 0, 0, 0, 0, 0, 0, 0, 0, 0, 0, 0, 0, 0, 0, 0, 0, 0, 0, 0, 0, 0, 0, 0, 0, 0, 0, 0, 0, 0, 0, 0, 0, 0, 0, 0, 0, 0, 0, 0, 0, 0, 0, 0, 0, 0, 0, 0, 0, 0, 0, 0, 0, 0, 0, 0, 0, 0, 0, 0, 0, 0, 41, 41, 41, 0, 0, 0, 0, 0, 0, 0, 0, 0, 0, 0, 0, 41, 41, 41, 41, 41, 41, 41, 0, 41, 41, 41, 41, 41, 41, 41, 41, 0, 0, 0, 0, 0, 41, 0, 0, 41, 0, 0, 41, 41, 41, 0, 0, 41, 0, 0, 0, 41, 0, 0, 0, 0, 0, 41, 0, 0, 41, 0, 0, 0, 0, 0, 0, 0, 41, 0, 0, 0, 41, 0, 0, 0, 0, 0, 41, 0, 0, 41, 0, 0, 0, 0, 0, 0, 0, 41, 0, 0, 0, 41, 0, 0, 0, 0, 0, 41, 41, 41, 41, 41, 41, 41, 41, 41, 41, 41, 41, 41, 41, 41, 41, 0, 0, 0, 0, 0, 0, 0, 0, 0, 0, 0, 0, 0, 0, 0, 0, 0, 0, 0, 0, 0, 0, 0, 0, 0, 0, 0, 0, 0, 0, 0, 0, 0, 0, 0, 0, 0, 0, 0, 0, 0, 0, 0, 0],
         "height":11,
         "id":16,
         "name":"Pathfind",
         "opacity":0.5,
         "properties":[
                {
                 "name":"pathfind",
                 "type":"bool",
                 "value":true
                }],
         "type":"tilelayer",
         "visible":true,
         "width":21,
         "x":0,
         "y":0
        }],
 "nextlayerid":20,
 "nextobjectid":75,
 "orientation":"orthogonal",
 "renderorder":"right-down",
 "tiledversion":"1.2.3",
 "tileheight":32,
 "tilesets":[
        {
         "firstgid":1,
         "source":"..\/tilesets\/TilesetDungeon1.tsx"
        }],
 "tilewidth":32,
 "type":"map",
 "version":1.2,
 "width":21
}